testeTp.v
module tp1isl (entrada, saida);
    input [0:4] entrada;
    output reg [0:6] saida;

    always @* begin
        case(entrada)
            5'b00000: saida = 7'b1011011;
            5'b00001: saida = 7'b1111011;
            5'b00010: saida = 7'b1010100;
            5'b00011: saida = 7'b1001110;
            5'b00100: saida = 7'b0101010;
            5'b00101: saida = 7'b1111111;
            5'b00110: saida = 7'b1101101;
            5'b00111: saida = 7'b0011111;
            5'b01000: saida = 7'b1000111;
            5'b01001: saida = 7'b1100111;
            5'b01010: saida = 7'b1011011;
            5'b01011: saida = 7'b0110111;
            5'b01100: saida = 7'b0110111;
            5'b01101: saida = 7'b1111011;
            5'b01110: saida = 7'b1011111;
            5'b01111: saida = 7'b0011100;
            5'b10000: saida = 7'b0010101;
            5'b10001: saida = 7'b1110011;
            5'b10010: saida = 7'b1110000;
            5'b10011: saida = 7'b1111110;
            default: saida =  7'b0000000;
        endcase
    end
endmodule

testeTp_tb.v
module testeTp_tb;
reg [0:4] inp_teste;
wire [0:6] out_saida;

tp1isl uut (.entrada(inp_teste), .saida(out_saida));

initial begin
        $dumpfile("testeTp_tb.vcd");
        $dumpvars(0, testeTp_tb);
        $display("Comeco");

        #0 inp_teste = 5'b00000;
        $monitor("Entrada %b - Saida = %b", inp_teste, out_saida);
        #1 inp_teste = 5'b00001;
        $monitor("Entrada %b - Saida = %b", inp_teste, out_saida);
        #1 inp_teste = 5'b00010;
        $monitor("Entrada %b - Saida = %b", inp_teste, out_saida);
        #1 inp_teste = 5'b00011;
        $monitor("Entrada %b - Saida = %b", inp_teste, out_saida);
        #1 inp_teste = 5'b00100;
        $monitor("Entrada %b - Saida = %b", inp_teste, out_saida);
        #1 inp_teste = 5'b00101;
        $monitor("Entrada %b - Saida = %b", inp_teste, out_saida);
        #1 inp_teste = 5'b00110;
        $monitor("Entrada %b - Saida = %b", inp_teste, out_saida);
        #1 inp_teste = 5'b00111;
        $monitor("Entrada %b - Saida = %b", inp_teste, out_saida);
        #1 inp_teste = 5'b01000;
        $monitor("Entrada %b - Saida = %b", inp_teste, out_saida);
        #1 inp_teste = 5'b01001;
        $monitor("Entrada %b - Saida = %b", inp_teste, out_saida);
        #1 inp_teste = 5'b01010;
        $monitor("Entrada %b - Saida = %b", inp_teste, out_saida);
        #1 inp_teste = 5'b01011;
        $monitor("Entrada %b - Saida = %b", inp_teste, out_saida);
        #1 inp_teste = 5'b01100;
        $monitor("Entrada %b - Saida = %b", inp_teste, out_saida);
        #1 inp_teste = 5'b01101;
        $monitor("Entrada %b - Saida = %b", inp_teste, out_saida);
        #1 inp_teste = 5'b01110;
        $monitor("Entrada %b - Saida = %b", inp_teste, out_saida);
        #1 inp_teste = 5'b01111;
        $monitor("Entrada %b - Saida = %b", inp_teste, out_saida);
        #1 inp_teste = 5'b10000;
        $monitor("Entrada %b - Saida = %b", inp_teste, out_saida);
        #1 inp_teste = 5'b10001;
        $monitor("Entrada %b - Saida = %b", inp_teste, out_saida);
        #1 inp_teste = 5'b10010;
        $monitor("Entrada %b - Saida = %b", inp_teste, out_saida);
        #1 inp_teste = 5'b10011;
        $monitor("Entrada %b - Saida = %b", inp_teste, out_saida);
        #1 inp_teste = 5'b10100;
        $monitor("Entrada %b - Saida = %b", inp_teste, out_saida);
        #1 inp_teste = 5'b10101;
        $monitor("Entrada %b - Saida = %b", inp_teste, out_saida);
        #1 inp_teste = 5'b10110;
        $monitor("Entrada %b - Saida = %b", inp_teste, out_saida);
        #1 inp_teste = 5'b10111;
        $monitor("Entrada %b - Saida = %b", inp_teste, out_saida);
        #1 inp_teste = 5'b11000;
        $monitor("Entrada %b - Saida = %b", inp_teste, out_saida);
        #1 inp_teste = 5'b11001;
        $monitor("Entrada %b - Saida = %b", inp_teste, out_saida);
        #1 inp_teste = 5'b11010;
        $monitor("Entrada %b - Saida = %b", inp_teste, out_saida);
        #1 inp_teste = 5'b11011;
        $monitor("Entrada %b - Saida = %b", inp_teste, out_saida);
        #1 inp_teste = 5'b11100;
        $monitor("Entrada %b - Saida = %b", inp_teste, out_saida);
        #1 inp_teste = 5'b11101;
        $monitor("Entrada %b - Saida = %b", inp_teste, out_saida);
        #1 inp_teste = 5'b11110;
        $monitor("Entrada %b - Saida = %b", inp_teste, out_saida);
        #1 inp_teste = 5'b11111;
        $monitor("Entrada %b - Saida = %b", inp_teste, out_saida);
        #10 $stop;
        $display("Fim");
    end

endmodule

obsoletos/testeTp_tb.vcd
$date
	Tue Feb 15 20:20:18 2022
$end
$version
	Icarus Verilog
$end
$timescale
	1s
$end
$scope module testeTp_tb $end
$var wire 7 ! out_saida [0:6] $end
$var reg 5 " inp_teste [0:4] $end
$scope module uut $end
$var wire 5 # entrada [0:4] $end
$var reg 7 $ saida [0:6] $end
$upscope $end
$upscope $end
$enddefinitions $end
#0
$dumpvars
b1011011 $
b0 #
b0 "
b1011011 !
$end
#1
b1010100 $
b1010100 !
b10 "
b10 #
#2
b1111011 $
b1111011 !
b1 "
b1 #
#3
b1001110 $
b1001110 !
b11 "
b11 #
#4
b101010 $
b101010 !
b100 "
b100 #
#5
b1111111 $
b1111111 !
b101 "
b101 #
#6
b1101101 $
b1101101 !
b110 "
b110 #
#7
b11111 $
b11111 !
b111 "
b111 #
#8
b1000111 $
b1000111 !
b1000 "
b1000 #
#9
b1100111 $
b1100111 !
b1001 "
b1001 #
#10
b1011011 $
b1011011 !
b1010 "
b1010 #
#11
b110111 $
b110111 !
b1011 "
b1011 #
#12
b1100 "
b1100 #
#13
b1111011 $
b1111011 !
b1101 "
b1101 #
#14
b1011111 $
b1011111 !
b1110 "
b1110 #
#15
b11100 $
b11100 !
b1111 "
b1111 #
#16
b10101 $
b10101 !
b10000 "
b10000 #
#17
b1110011 $
b1110011 !
b10001 "
b10001 #
#18
b1110000 $
b1110000 !
b10010 "
b10010 #
#19
b1111110 $
b1111110 !
b10011 "
b10011 #
#20
b0 $
b0 !
b10100 "
b10100 #
#21
b10101 "
b10101 #
#22
b10110 "
b10110 #
#23
b10111 "
b10111 #
#24
b11000 "
b11000 #
#25
b11001 "
b11001 #
#26
b11010 "
b11010 #
#27
b11011 "
b11011 #
#28
b11100 "
b11100 #
#29
b11101 "
b11101 #
#30
b11110 "
b11110 #
#31
b11111 "
b11111 #
